monolith/__init__.py
monolith/compat.py
monolith/__pycache__/__init__.cpython-33.pyc
monolith/__pycache__/compat.cpython-33.pyc
monolith/cli/__init__.py
monolith/cli/base.py
monolith/cli/completion.py
monolith/cli/exceptions.py
monolith/cli/__pycache__/__init__.cpython-33.pyc
monolith/cli/__pycache__/base.cpython-33.pyc
monolith/cli/__pycache__/completion.cpython-33.pyc
monolith/cli/__pycache__/exceptions.cpython-33.pyc
monolith/tests/__init__.py
monolith/tests/__main__.py
monolith/tests/test_cli.py
monolith/tests/test_cli_completion.py
monolith/utils/__init__.py
monolith/utils/imports.py
monolith/utils/ordereddict.py
monolith/utils/__pycache__/__init__.cpython-33.pyc
monolith/utils/__pycache__/imports.cpython-33.pyc
monolith-0.3.3.dist-info/DESCRIPTION.rst
monolith-0.3.3.dist-info/METADATA
monolith-0.3.3.dist-info/pydist.json
monolith-0.3.3.dist-info/RECORD
monolith-0.3.3.dist-info/top_level.txt
monolith-0.3.3.dist-info/WHEEL
monolith.egg-info/dependency_links.txt
monolith.egg-info/not-zip-safe
monolith.egg-info/PKG-INFO
monolith.egg-info/SOURCES.txt
monolith.egg-info/top_level.txt
