Metadata-Version: 2.0
Name: monolith
Version: 0.3.3
Summary: 
